pyscail/__init__.py
pyscail/graphics.py
pyscail/grid.py
pyscail/kernels.py
pyscail/pyscail.py
pyscail/settings.py
pyscail-0.1.0.dist-info/METADATA
pyscail-0.1.0.dist-info/WHEEL
pyscail-0.1.0.dist-info/licenses/LICENSE
pyscail-0.1.0.dist-info/RECORD
