Metadata-Version: 2.3
Name: pyscail
Version: 0.1.0
Summary: A package that helps build cellular automata
Project-URL: Homepage, https://github.com/ribhuhooja/pyscail
Project-URL: Issues, https://github.com/ribhuhooja/pyscail/issues
Author-email: Ribhu Hooja <ribhu.hooja.27@dartmouth.edu>
License-File: LICENSE
Keywords: cellular automata,game of life
Classifier: License :: OSI Approved :: MIT License
Classifier: Operating System :: OS Independent
Classifier: Programming Language :: Python :: 3
Requires-Python: >=3.11
Requires-Dist: pygame
